{
"Title": "Team Members",
"ColumnHeaders" :
[
"ID",
"Name",
"Role",
"Nickname",
"Salary"
],
"Data" :
[
{
"ID" : "001",
"Name" : "John Doe",
"Role" : "Engineer",
"Nickname" : "KillerJo",
"Salary":"12313"
},
{
"ID" : "023",
"Name" : "Claire Dawn",
"Role" : "Engineer",
"Nickname" : "Claw",
"Salary":"900"
},
{
"ID" : "012",
"Name" : "Paul Beef",
"Role" : "Designer",
"Nickname" : "BeefyPaul",
"Salary":"10"

},
{
"ID" : "056",
"Name" : "Sally Sue",
"Role" : "Artist",
"Nickname" : "Sue5555",
"Salary":"-1"
},
]
}
